{
  "core": {
    "minified": {
      "pretty": "343 B",
      "raw": 343
    },
    "brotli": {
      "pretty": "213 B",
      "raw": 213
    }
  },
  "evaluator": {
    "minified": {
      "pretty": "708 B",
      "raw": 708
    },
    "brotli": {
      "pretty": "392 B",
      "raw": 392
    }
  },
  "reactivity": {
    "minified": {
      "pretty": "4.73 kB",
      "raw": 4728
    },
    "brotli": {
      "pretty": "1.61 kB",
      "raw": 1615
    }
  },
  "alpinejs": {
    "minified": {
      "pretty": "35.9 kB",
      "raw": 35865
    },
    "brotli": {
      "pretty": "11.9 kB",
      "raw": 11948
    }
  }
}